{
    "pointers": [
        {"id":1,"description":"hand-right-small-shadow-only", "x":51,"y":128,"w":37,"h":32, "palette": 2},
        {"id":1,"description":"hand-cancel-with-shadow", "x":80,"y":32,"w":48,"h":32, "palette": 8}
    ],
    "icons-menu": [
        {"id":1, "description":"item", "x":192,"y":224,"w":26,"h":32, "palette": 2},
        {"id":1, "description":"sword", "x":224,"y":224,"w":26,"h":32, "palette": 2}
    ],
    "materia": [
        {"id":1, "description":"slot-nogrowth", "x":224,"y":64,"w":24,"h":24, "palette": 2},
        {"id":1, "description":"slot-join", "x":227,"y":96,"w":14,"h":24, "palette": 2}
    ]
}